owlfft.py
owlfft-0.0.7.dist-info/METADATA
owlfft-0.0.7.dist-info/WHEEL
owlfft-0.0.7.dist-info/RECORD
