Metadata-Version: 2.4
Name: owlfft
Version: 0.0.7
Summary: Wrap numpy.fft and numpy.loadtxt within a simple GUI
Project-URL: Homepage, https://miguelmaso.github.io/dynamics/
Project-URL: Repository, https://github.com/miguelmaso/dynamics/tree/main/tools
Author-email: Miguel Masó <miguel.maso@upc.edu>
License: MIT License
Keywords: Fourier transform,structural dynamics,teaching
Requires-Python: >=3
Requires-Dist: matplotlib
Requires-Dist: numpy
Requires-Dist: pyqt5
Requires-Dist: superqt
